machupX/__init__.py
machupX/__main__.py
machupX/airplane.py
machupX/dxf.py
machupX/exceptions.py
machupX/helpers.py
machupX/poly_fits.py
machupX/scene.py
machupX/standard_atmosphere.py
machupX/wing_segment.py
machupx_web-2.7.2.dist-info/licenses/LICENSE
machupx_web-2.7.2.dist-info/METADATA
machupx_web-2.7.2.dist-info/WHEEL
machupx_web-2.7.2.dist-info/top_level.txt
machupx_web-2.7.2.dist-info/RECORD
