Metadata-Version: 2.4
Name: MachUpX-web
Version: 2.7.2
Summary: A web wrapper for MachUpX: An implementation of the Goates-Hunsaker generalized numerical lifting-line algorithm.
Home-page: https://github.com/usuaero/MachUpX
Author: usuaero
Author-email: doug.hunsaker@usu.edu
License: MIT
Requires-Python: >=3.6.0
License-File: LICENSE
Requires-Dist: numpy>=1.18
Requires-Dist: scipy>=1.4
Requires-Dist: pytest
Requires-Dist: matplotlib
Requires-Dist: numpy-stl
Requires-Dist: airfoil_db>=1.4.3
Dynamic: author
Dynamic: author-email
Dynamic: home-page
Dynamic: license
Dynamic: license-file
Dynamic: requires-dist
Dynamic: requires-python
Dynamic: summary
